MANIFEST.in
README.rst
setup.py
aliyun_python_sdk_trademark.egg-info/PKG-INFO
aliyun_python_sdk_trademark.egg-info/SOURCES.txt
aliyun_python_sdk_trademark.egg-info/dependency_links.txt
aliyun_python_sdk_trademark.egg-info/requires.txt
aliyun_python_sdk_trademark.egg-info/top_level.txt
aliyunsdktrademark/__init__.py
aliyunsdktrademark/request/__init__.py
aliyunsdktrademark/request/v20180724/ApplyNotaryPostRequest.py
aliyunsdktrademark/request/v20180724/BindMaterialRequest.py
aliyunsdktrademark/request/v20180724/CancelTradeOrderRequest.py
aliyunsdktrademark/request/v20180724/CheckLoaFillRequest.py
aliyunsdktrademark/request/v20180724/CombineLoaRequest.py
aliyunsdktrademark/request/v20180724/ConvertImageToGrayRequest.py
aliyunsdktrademark/request/v20180724/CreateTrademarkOrderRequest.py
aliyunsdktrademark/request/v20180724/DeleteMaterialRequest.py
aliyunsdktrademark/request/v20180724/DeleteTmMonitorRuleRequest.py
aliyunsdktrademark/request/v20180724/DenySupplementRequest.py
aliyunsdktrademark/request/v20180724/FillLogisticsRequest.py
aliyunsdktrademark/request/v20180724/FilterUnavailableCodesRequest.py
aliyunsdktrademark/request/v20180724/GenerateQrCodeRequest.py
aliyunsdktrademark/request/v20180724/GenerateUploadFilePolicyRequest.py
aliyunsdktrademark/request/v20180724/GetNotaryOrderRequest.py
aliyunsdktrademark/request/v20180724/InsertMaterialRequest.py
aliyunsdktrademark/request/v20180724/InsertRenewInfoRequest.py
aliyunsdktrademark/request/v20180724/InsertTmMonitorRuleRequest.py
aliyunsdktrademark/request/v20180724/InsertTradeIntentionUserRequest.py
aliyunsdktrademark/request/v20180724/ListNotaryInfosRequest.py
aliyunsdktrademark/request/v20180724/ListNotaryOrdersRequest.py
aliyunsdktrademark/request/v20180724/QueryCommunicationLogsRequest.py
aliyunsdktrademark/request/v20180724/QueryCredentialsInfoRequest.py
aliyunsdktrademark/request/v20180724/QueryMaterialListRequest.py
aliyunsdktrademark/request/v20180724/QueryMaterialRequest.py
aliyunsdktrademark/request/v20180724/QueryMonitorKeywordsRequest.py
aliyunsdktrademark/request/v20180724/QueryOssResourcesRequest.py
aliyunsdktrademark/request/v20180724/QueryQrCodeUploadStatusRequest.py
aliyunsdktrademark/request/v20180724/QuerySupplementDetailRequest.py
